{
  "resourceType": "PlanDefinition",
  "id": "ColoRectal",
  "meta": {
    "profile": [
      "http://hl7.org.nz/fhir/StructureDefinition/CcaPlanDefinition"
    ]
  },
  "extension": [
    {
      "url": "http://clinfhir.com/fhir/StructureDefinition/plan-instructions",
      "valueMarkdown": "Only for women"
    },
    {
      "url": "http://clinfhir.com/fhir/StructureDefinition/regimen-type",
      "valueCodeableConcept": {
        "text": "Folfox"
      }
    },
    {
      "extension": [
        {
          "url": "factor",
          "valueCodeableConcept": {
            "coding": [
              {
                "code": "TOUPDATE-SUPPORT4",
                "system": "http://snomed.info/sct",
                "display": "Diarrhoea risk"
              }
            ]
          }
        },
        {
          "url": "value",
          "valueCodeableConcept": {
            "text": "low"
          }
        }
      ],
      "url": "http://clinfhir.com/fhir/StructureDefinition/support-factor"
    },
    {
      "extension": [
        {
          "url": "factor",
          "valueCodeableConcept": {
            "coding": [
              {
                "code": "TOUPDATE-SUPPORT8",
                "system": "http://snomed.info/sct",
                "display": "AntiFungal Prophylaxis"
              }
            ]
          }
        },
        {
          "url": "value",
          "valueCodeableConcept": {
            "text": "low"
          }
        }
      ],
      "url": "http://clinfhir.com/fhir/StructureDefinition/support-factor"
    },
    {
      "extension": [
        {
          "url": "factor",
          "valueCodeableConcept": {
            "coding": [
              {
                "code": "TOUPDATE-SUPPORT2",
                "system": "http://snomed.info/sct",
                "display": "Hypersensitivity / Infusion related reaction ris"
              }
            ]
          }
        },
        {
          "url": "value",
          "valueCodeableConcept": {
            "text": "low"
          }
        }
      ],
      "url": "http://clinfhir.com/fhir/StructureDefinition/support-factor"
    }
  ],
  "_status": {
    "extension": [
      {
        "url": "http://clinfhir.com/fhir/StructureDefinition/regimen-under-review",
        "valueCode": "review"
      }
    ]
  },
  "type": {
    "coding": [
      {
        "code": "clinical-protocol",
        "system": "http://terminology.hl7.org/CodeSystem/plan-definition-type"
      }
    ]
  },
  "action": [
    {
      "extension": [
        {
          "url": "http://clinfhir.com/fhir/StructureDefinition/disclaimer",
          "valueString": "Ensure not pregnant before starting"
        },
        {
          "url": "http://clinfhir.com/fhir/StructureDefinition/plan-instructions",
          "valueMarkdown": "Ensure not pregnant before starting"
        }
      ],
      "action": [
        {
          "extension": [
            {
              "url": "http://clinfhir.com/fhir/StructureDefinition/plan-instructions",
              "valueMarkdown": "Keep a close eye for side effects"
            },
            {
              "extension": [
                {
                  "url": "day",
                  "valueInteger": 1
                },
                {
                  "url": "instructions",
                  "valueString": "Specific instructions for the first administration"
                }
              ],
              "url": "http://clinfhir.com/fhir/StructureDefinition/timing-of-days"
            },
            {
              "extension": [
                {
                  "url": "day",
                  "valueInteger": 4
                },
                {
                  "url": "instructions",
                  "valueString": "Specific instructions for the second administration"
                }
              ],
              "url": "http://clinfhir.com/fhir/StructureDefinition/timing-of-days"
            }
          ],
          "definitionCanonical": "#act-cabergoline",
          "description": "2mg of Cabergoline daily on days 1 and 4 by IV Infusion over 20 minutes"
        },
        {
          "extension": [
            {
              "extension": [
                {
                  "url": "day",
                  "valueInteger": 2
                },
                {
                  "url": "instructions",
                  "valueString": "Specific instructions for the first administration"
                }
              ],
              "url": "http://clinfhir.com/fhir/StructureDefinition/timing-of-days"
            },
            {
              "extension": [
                {
                  "url": "day",
                  "valueInteger": 3
                },
                {
                  "url": "instructions",
                  "valueString": "Specific instructions for the second administration"
                }
              ],
              "url": "http://clinfhir.com/fhir/StructureDefinition/timing-of-days"
            },
            {
              "extension": [
                {
                  "url": "day",
                  "valueInteger": 4
                },
                {
                  "url": "instructions",
                  "valueString": "Specific instructions for the third administration"
                }
              ],
              "url": "http://clinfhir.com/fhir/StructureDefinition/timing-of-days"
            }
          ],
          "definitionCanonical": "#act-tragacanth",
          "description": "3mg of Tragacanth daily on days 2,3 and 4 by IV Infusion over 3 hours"
        }
      ],
      "description": "Administration of Cabergoline and Tragacanth. Cycle length 14 days",
      "title": "This is the only cycle in the regimen.",
      "selectionBehavior": "all",
      "timingTiming": {
        "repeat": {
          "count": 1,
          "duration": 14,
          "durationUnit": "d"
        }
      }
    }
  ],
  "text": {
    "div": "<div xmlns=\"http://www.w3.org/1999/xhtml\">Plan for ColoRectal cancer. Therer is a single cycle with 2 drug administrations</div>",
    "status": "additional"
  },
  "status": "active",
  "version": "3.0.3",
  "title": "Colorectal Adjuvant FOLFOX (a7)",
  "description": "A drug treatment regimen for Colorectal cancer",
  "publisher": "New Zealand Medicines Formulary LP",
  "date": "2020-06-29T20:14:18.417+12:00",
  "experimental": false,
  "contained": [
    {
      "resourceType": "ActivityDefinition",
      "id": "ActTragacanth",
      "meta": {
        "profile": [
          "http://hl7.org.nz/fhir/StructureDefinition/CcaActivityDefinition"
        ]
      },
      "text": {
        "div": "<div xmlns=\"http://www.w3.org/1999/xhtml\">Tragacanth administration, 3mg over 3 hours by continuous IV infusion</div>",
        "status": "additional"
      },
      "productCodeableConcept": {
        "coding": [
          {
            "code": "10711851000116105",
            "system": "https://nzulm.org.nz/nzmt",
            "display": "Tragacanth"
          }
        ]
      },
      "dosage": [
        {
          "text": "3 mg over 3 hours by IV infusion",
          "route": {
            "coding": [
              {
                "code": "180177004",
                "system": "http://snomed.info/sct",
                "display": "continuous intravenous infusion"
              }
            ]
          },
          "doseAndRate": [
            {
              "doseQuantity": {
                "value": 3,
                "system": "http://unitsofmeasure.org",
                "code": "mg"
              },
              "rateQuantity": {
                "value": 3,
                "system": "http://unitsofmeasure.org",
                "code": "h"
              }
            }
          ]
        }
      ],
      "status": "draft"
    }
  ],
  "useContext": [
    {
      "code": {
        "code": "focus",
        "system": "http://terminology.hl7.org/CodeSystem/usage-context-type"
      },
      "valueCodeableConcept": {
        "coding": [
          {
            "code": "781382000",
            "system": "http://snomed.info/sct",
            "display": "Colorectal cancer"
          }
        ]
      }
    }
  ],
  "relatedArtifact": [
    {
      "type": "citation",
      "display": "test",
      "url": "http://www.ncbi.nlm.nih.gov/pubmed/23434"
    },
    {
      "type": "citation",
      "display": "test2",
      "url": "http://www.ncbi.nlm.nih.gov/pubmed/34324"
    }
  ]
}
